<?xml version="1.0" encoding="UTF-8"?>
<resources>
  <string name="mb_camera_permission_required">É necessária a permissão de acesso à câmara.</string>
  <string name="mb_close">Fechar</string>
  <string name="mb_dialog_back_button">Anterior</string>
  <string name="mb_dialog_done_button">Concluído</string>
  <string name="mb_dialog_next_button">Seguinte</string>
  <string name="mb_dialog_skip_button">Ignorar</string>
  <string name="mb_enable_camera">Ative a câmara</string>
  <string name="mb_enable_permission_help">Vai ser redirecionado para as configurações de permissão, onde tem de dar permissão à aplicação para acesso à câmara.</string>
  <string name="mb_enable_permission_help_instant_app">Dê permissão de acesso à câmara nas configurações de permissão da aplicação.</string>
  <string name="mb_license_locked">Digitalização não disponível</string>
  <string name="mb_loading">Carregando…</string>
  <string name="mb_move_closer">Aproxime</string>
  <string name="mb_move_farther">Afaste</string>
  <string name="mb_need_help_tooltip">Precisa de ajuda?</string>
  <string name="mb_ok">OK</string>
  <string name="mb_retry">Tente novamente</string>
  <string name="mb_warning">Aviso</string>
</resources>
